{
  "name": "Axel",
  "username": "AnzenKodo",
  "email": "AnzenKodo@altmails.com",
  "description": "Programming nerd who is obsessed with JavaScript.",
  "location": "Mom's basement",
  "age": "ಠ_ಠ",
  "hobby": "Making fun stuff.",
  "website": "https://AnzenKodo.github.io/",
  "color": "f20544",
  "logo": "https://AnzenKodo.github.io/assets/ak/logo",
  "mascot": "https://AnzenKodo.github.io/assets/ak/mascot",
  "banner": "https://i.pinimg.com/originals/80/72/88/80728890ac2a538015c923b507718c99.jpg",
  "wallpaper": "https://i.pinimg.com/originals/21/6e/24/216e2426530a08d6788cf2d73ca8f6ba.jpg",
  "browserWallpaper": "https://i.pinimg.com/originals/c3/17/b6/c317b65caa672d30a4a52e72144e4fad.jpg",
  "socials": {
    "GitHub": "https://github.com/AnzenKodo",
    "Replit": "https://replit.com/@AnzenKodo",
    "Twitter": "https://twitter.com/AnzenKodo",
    "Discord ": "https://discord.com/users/910257548593086474",
    "Pinterest": "https://www.pinterest.com/AnzenKodo/",
    "Goodreads": "https://www.goodreads.com/AnzenKodo",
    "Simkl": "https://simkl.com/5607531/",
    "ListenBrainz": "https://listenbrainz.org/user/AnzenKodo/"
  },
  "languages": [
    "HTML",
    "JavaScript",
    "CSS",
    "PHP",
    "Shell",
    "Nix",
    "Nunjucks",
    "Jupyter Notebook",
    "Java",
    "Python"
  ],
  "todo": {
    "working": [
      "[ ] AK#Db data from markdown"
    ],
    "next": [
      "[ ] Track everything",
      "  [ ] App Installed",
      "  [ ] Phone Usage",
      "  [ ] Computer Usage",
      "  [ ] Sends music data",
      "[ ] Table of Content on all the sites",
      "[ ] API's",
      "  [ ] Pinboard",
      "  [ ] Bookmarks",
      "  [ ] Extenstions"
    ]
  },
  "support": {
    "ethereum": "0xE9421ad603651a6ecD56d3C78472E64EDE7Cf43A"
  },
  "site": {
    "notes": "https://anzenkodo.substack.com/",
    "todo": "https://AnzenKodo.github.io/todo",
    "db": "https://AnzenKodo.github.io/db",
    "pinboard": "https://AnzenKodo.github.io/pinboard",
    "awesome": "https://AnzenKodo.github.io/awesome"
  },
  "api": {
    "notes": "https://anzenkodo.substack.com/feed",
    "db": "https://AnzenKodo.github.io/api/db.json",
    "pinboard": "https://AnzenKodo.github.io/api/pinboard.json",
    "blogroll": "https://AnzenKodo.github.io/api/blogroll.json",
    "github": "https://api.github.com/users/AnzenKodo",
    "bookmarks": "https://github.com/AnzenKodo/dotfiles/blob/master/browser/Bookmarks.bak"
  }
}